morgan/__about__.py
morgan/__init__.py
morgan/__main__.py
morgan/configurator.py
morgan/metadata.py
morgan/server.py
morgan/utils.py
morgan-0.14.4.dist-info/METADATA
morgan-0.14.4.dist-info/WHEEL
morgan-0.14.4.dist-info/entry_points.txt
morgan-0.14.4.dist-info/licenses/LICENSE
morgan-0.14.4.dist-info/RECORD
