Metadata-Version: 2.4
Name: morgan
Version: 0.14.4
Summary: PyPI Mirror for Offline/Restricted Environments
Project-URL: Homepage, https://github.com/ido50/morgan
Project-URL: Repository, https://github.com/ido50/morgan
Project-URL: Bug Tracker, https://github.com/ido50/morgan/issues
Project-URL: Changelog, https://github.com/ido50/morgan/releases
Author-email: Ido Perlmuter <ido@ido50.net>
License: 
License-File: LICENSE
Keywords: mirror,packages,pypi,pypi-mirror
Classifier: Development Status :: 4 - Beta
Classifier: Intended Audience :: Developers
Classifier: Intended Audience :: Information Technology
Classifier: Intended Audience :: System Administrators
Classifier: License :: OSI Approved :: Apache Software License
Classifier: Natural Language :: English
Classifier: Operating System :: OS Independent
Classifier: Programming Language :: Python :: 3 :: Only
Classifier: Programming Language :: Python :: 3.7
Classifier: Programming Language :: Python :: 3.8
Classifier: Programming Language :: Python :: 3.9
Classifier: Programming Language :: Python :: 3.10
Classifier: Programming Language :: Python :: Implementation :: CPython
Classifier: Topic :: Internet :: WWW/HTTP :: HTTP Servers
Requires-Python: >=3.7
Requires-Dist: importlib-metadata~=4.12.0; python_version < '3.8'
Requires-Dist: packaging~=24.2
Requires-Dist: tomli~=2.0.1
Provides-Extra: test
Requires-Dist: pytest~=7.1.3; extra == 'test'
